.VERSION
AUTHORS.rst
CONTRIBUTING.rst
HISTORY.rst
LICENSE
MANIFEST.in
Pipfile
Pipfile.lock
README.rst
USAGE.rst
dev-requirements.txt
requirements.txt
setup.cfg
setup.py
docs/Makefile
docs/authors.rst
docs/conf.py
docs/contributing.rst
docs/history.rst
docs/index.rst
docs/installation.rst
docs/modules.rst
docs/prereceivecli.lib.rst
docs/prereceivecli.rst
docs/readme.rst
docs/usage.rst
prereceivecli/.VERSION
prereceivecli/AUTHORS.rst
prereceivecli/CONTRIBUTING.rst
prereceivecli/HISTORY.rst
prereceivecli/LICENSE
prereceivecli/Pipfile
prereceivecli/Pipfile.lock
prereceivecli/README.rst
prereceivecli/USAGE.rst
prereceivecli/__init__.py
prereceivecli/_version.py
prereceivecli/configuration.py
prereceivecli/dev-requirements.txt
prereceivecli/prereceivecli.py
prereceivecli/prereceivecliexceptions.py
prereceivecli/requirements.txt
prereceivecli.egg-info/PKG-INFO
prereceivecli.egg-info/SOURCES.txt
prereceivecli.egg-info/dependency_links.txt
prereceivecli.egg-info/entry_points.txt
prereceivecli.egg-info/not-zip-safe
prereceivecli.egg-info/requires.txt
prereceivecli.egg-info/top_level.txt
prereceivecli/__pycache__/__init__.cpython-37.pyc
prereceivecli/__pycache__/_version.cpython-37.pyc
prereceivecli/__pycache__/configuration.cpython-37.pyc
prereceivecli/__pycache__/prereceivecliexceptions.cpython-37.pyc
prereceivecli/conf/logging.json
prereceivecli/lib/__init__.py
prereceivecli/lib/utils.py
prereceivecli/lib/__pycache__/__init__.cpython-37.pyc
prereceivecli/lib/__pycache__/utils.cpython-37.pyc