Metadata-Version: 1.1
Name: prereceivecli
Version: 1.0.0
Summary: A cli that implements a git server side pre-receive hook that gets driven from dynamodb and reports to slack offending pushes.
Home-page: https://github.com/schubergphilis/prereceivecli.git
Author: Costas Tyfoxylos
Author-email: ctyfoxylos@schubergphilis.com
License: MIT
Keywords: prereceivecli git hook serverside pre receive
Platform: UNKNOWN
Classifier: Development Status :: 4 - Beta
Classifier: Intended Audience :: Developers
Classifier: License :: OSI Approved :: MIT License
Classifier: Natural Language :: English
Classifier: Programming Language :: Python :: 3.7
